localreplitdb/__init__.py
localreplitdb/localreplitdb.py
localreplitdb/realreplitdb.py
replit-py/src/replit/database/database.py
localreplitdb-0.0.2.dist-info/LICENSE
localreplitdb-0.0.2.dist-info/METADATA
localreplitdb-0.0.2.dist-info/WHEEL
localreplitdb-0.0.2.dist-info/RECORD
